admin_info/__init__.py
admin_info/static/css/foldable_admin.css
admin_info/static/js/foldable_admin.js
admin_info/templates/admin/change_list.html
admin_info/templates/admin/foldable_admin.html
admin_info/templates/admin/index.html
admin_info/templates/admin/summary.tpl
admin_info/templatetags/custom_tags.py
django_admin_info-0.0.5.dist-info/LICENSE
django_admin_info-0.0.5.dist-info/METADATA
django_admin_info-0.0.5.dist-info/WHEEL
django_admin_info-0.0.5.dist-info/top_level.txt
django_admin_info-0.0.5.dist-info/RECORD
