Metadata-Version: 2.1
Name: django-admin-info
Version: 0.0.5
Summary: Simple Collapsible Admin view for Django with model information.
Home-page: https://github.com/nilesh-kr-dubey/django-admin-info
Author: Nilesh Kumar Dubey
Author-email: nileshdubeyindia@gmail.com
License: MIT
Platform: UNKNOWN
Classifier: Environment :: Web Environment
Classifier: Framework :: Django
Classifier: Intended Audience :: Developers
Classifier: License :: OSI Approved :: MIT License
Classifier: Programming Language :: Python :: 3.6
Classifier: Programming Language :: Python :: 3.7
Classifier: Programming Language :: Python :: 3.8
Classifier: Topic :: Internet :: WWW/HTTP
Classifier: Topic :: Internet :: WWW/HTTP :: Dynamic Content
Requires-Dist: Django (>=1.7)
